odoo/addons/budget_control_request_document_expense/README.rst
odoo/addons/budget_control_request_document_expense/__init__.py
odoo/addons/budget_control_request_document_expense/__manifest__.py
odoo/addons/budget_control_request_document_expense/models/__init__.py
odoo/addons/budget_control_request_document_expense/models/base_budget_move.py
odoo/addons/budget_control_request_document_expense/models/hr_expense.py
odoo/addons/budget_control_request_document_expense/models/request_document.py
odoo/addons/budget_control_request_document_expense/readme/CONTRIBUTORS.md
odoo/addons/budget_control_request_document_expense/readme/DESCRIPTION.md
odoo/addons/budget_control_request_document_expense/static/description/icon.png
odoo/addons/budget_control_request_document_expense/static/description/index.html
odoo/addons/budget_control_request_document_expense/tests/__init__.py
odoo/addons/budget_control_request_document_expense/tests/test_budget_control_request_expense.py
odoo_addon_budget_control_request_document_expense-18.0.1.0.0.1.dist-info/METADATA
odoo_addon_budget_control_request_document_expense-18.0.1.0.0.1.dist-info/WHEEL
odoo_addon_budget_control_request_document_expense-18.0.1.0.0.1.dist-info/top_level.txt
odoo_addon_budget_control_request_document_expense-18.0.1.0.0.1.dist-info/RECORD
